vclust.py
bin/clusty
bin/kmer-db
bin/lz-ani
bin/mfasta-tool
vclust-1.3.1.dist-info/licenses/LICENSE
vclust-1.3.1.dist-info/METADATA
vclust-1.3.1.dist-info/WHEEL
vclust-1.3.1.dist-info/entry_points.txt
vclust-1.3.1.dist-info/top_level.txt
vclust-1.3.1.dist-info/RECORD
