Metadata-Version: 2.4
Name: vclust
Version: 1.3.1
Summary: Fast and accurate tool for calculating Average Nucleotide Identity (ANI) and clustering virus genomes and metagenomic contigs
Author-email: Andrzej Zielezinski <andrzej.zielezinski@amu.edu.pl>, Adam Gudyś <adam.gudys@polsl.pl>, Sebastian Deorowicz <sebastian.deorowicz@polsl.pl>
License:                     GNU GENERAL PUBLIC LICENSE
Project-URL: Homepage, https://github.com/refresh-bio/vclust
Project-URL: Documentation, https://github.com/refresh-bio/vclust/wiki
Project-URL: Website, http://vclust.org
Classifier: Development Status :: 5 - Production/Stable
Classifier: Natural Language :: English
Classifier: Intended Audience :: Developers
Classifier: Intended Audience :: Science/Research
Classifier: Topic :: Scientific/Engineering
Classifier: Topic :: Scientific/Engineering :: Bio-Informatics
Classifier: Operating System :: POSIX :: Linux
Classifier: Operating System :: MacOS
Classifier: License :: OSI Approved :: GNU Affero General Public License v3
Classifier: Programming Language :: Python :: 3
Classifier: Programming Language :: Python :: 3.7
Classifier: Programming Language :: Python :: 3.8
Classifier: Programming Language :: Python :: 3.9
Classifier: Programming Language :: Python :: 3.10
Classifier: Programming Language :: Python :: 3.11
Classifier: Programming Language :: Python :: 3.12
Requires-Python: >=3.7
License-File: LICENSE
Dynamic: license-file
